LICENSE
MANIFEST.in
README.md
setup.py
docs/GOES_2020-01-28T16:10:00+00:00.png
docs/Makefile
docs/authors.rst
docs/conf.py
docs/contributing.rst
docs/history.rst
docs/index.rst
docs/installation.rst
docs/make.bat
docs/readme.rst
docs/usage.rst
tests/__init__.py
tests/test_worldview_dl.py
worldview_dl/__init__.py
worldview_dl/cli.py
worldview_dl/worldview_dl.py
worldview_dl.egg-info/PKG-INFO
worldview_dl.egg-info/SOURCES.txt
worldview_dl.egg-info/dependency_links.txt
worldview_dl.egg-info/entry_points.txt
worldview_dl.egg-info/not-zip-safe
worldview_dl.egg-info/requires.txt
worldview_dl.egg-info/top_level.txt