Metadata-Version: 2.1
Name: worldview-dl
Version: 0.2.0
Summary: Download utility for NASA WorldView
Home-page: https://github.com/leifdenby/worldview_dl
Author: Leif Denby
Author-email: leif@denby.eu
License: MIT license
Keywords: worldview_dl
Platform: UNKNOWN
Classifier: Development Status :: 2 - Pre-Alpha
Classifier: Intended Audience :: Developers
Classifier: License :: OSI Approved :: MIT License
Classifier: Natural Language :: English
Classifier: Programming Language :: Python :: 3
Classifier: Programming Language :: Python :: 3.5
Classifier: Programming Language :: Python :: 3.6
Classifier: Programming Language :: Python :: 3.7
Classifier: Programming Language :: Python :: 3.8
Requires-Python: >=3.5
